IkonGlobals/__init__.py
IkonGlobals/settings.py
IkonGlobals/database/__init__.py
IkonGlobals/database/campaign.py
IkonGlobals/database/song.py
IkonGlobals/database/speaker.py
IkonGlobals/database/speech.py
IkonGlobals/database/user.py
IkonGlobals/utils/__init__.py
IkonGlobals/utils/embedding_utils.py
IkonGlobals/utils/sentry_tool.py
IkonGlobals/utils/utils.py
IkonGlobals-1.0.3.dist-info/LICENSE
IkonGlobals-1.0.3.dist-info/METADATA
IkonGlobals-1.0.3.dist-info/WHEEL
IkonGlobals-1.0.3.dist-info/top_level.txt
IkonGlobals-1.0.3.dist-info/RECORD
