Metadata-Version: 2.1
Name: IkonGlobals
Version: 1.0.3
Summary: A package to hold all of the data structures and functions common to other ikon repos
Home-page: https://github.com/IkonAI-App/IkonGlobals
Author: Samuel Sallee
Author-email: samsallee16@gmail.com
Classifier: Programming Language :: Python :: 3
Classifier: License :: OSI Approved :: MIT License
Classifier: Operating System :: OS Independent
Requires-Python: >=3.9
License-File: LICENSE
Requires-Dist: pynamodb>=6.0.0
Requires-Dist: pynamodb-attributes>=0.5.0
Requires-Dist: pytz>=2022.7.1
Requires-Dist: boto3>=1.34.82
Requires-Dist: pycountry>=24.6.1
Requires-Dist: opensearch-py>=2.6.0
Requires-Dist: sentry-sdk>=2.16.0
Requires-Dist: Werkzeug==2.2.2
